<?xml version="1.0" encoding="UTF-8"?>
<feature
      id="de.uniol.inf.is.odysseus.wrapper.actisense.feature"
      label="Actisense Feature"
      version="1.0.0">

   <description url="http://www.example.com/description">
      [Enter Feature Description here.]
   </description>

   <copyright>
      Copyright by the Odysseus Team (odysseus.informatik.uni-oldenburg.de)
   </copyright>
   
   <license url="http://www.apache.org/licenses/LICENSE-2.0">
      Licensed under the Apache License, Version 2.0 (the &quot;License&quot;);
you may not use this file except in compliance with the License.
You may obtain a copy of the License at

    http://www.apache.org/licenses/LICENSE-2.0

Unless required by applicable law or agreed to in writing, software
distributed under the License is distributed on an &quot;AS IS&quot; BASIS,
WITHOUT WARRANTIES OR CONDITIONS OF ANY KIND, either express or implied.
See the License for the specific language governing permissions and
limitations under the License.
   </license>

   <url>
      <update label="Odysseus Update Site" url="http://odysseus.informatik.uni-oldenburg.de/update"/>
   </url>

   <requires>
      <import plugin="de.uniol.inf.is.odysseus.core" version="1.0.0" match="greaterOrEqual"/>
      <import plugin="de.uniol.inf.is.odysseus.core.server" version="1.0.0" match="greaterOrEqual"/>
      <import plugin="org.eclipse.osgi"/>
      <import plugin="de.uniol.inf.is.odysseus.slf4j"/>
   </requires>

   <plugin
         id="de.uniol.inf.is.odysseus.wrapper.actisense"
         download-size="0"
         install-size="0"
         version="0.0.0"
         unpack="false"/>

</feature>
